example.py
src/playmanity_TheLite/__init__.py
playmanity-0.1.0.dist-info/METADATA
playmanity-0.1.0.dist-info/WHEEL
playmanity-0.1.0.dist-info/licenses/LICENSE
playmanity-0.1.0.dist-info/RECORD
