Metadata-Version: 2.1
Name: playmanity
Version: 0.1.0
Summary: Playmanity.py is a Python library for using and creating api scripts & programs with integration of playmanity services
Author-email: TheLite <thelitestudio0@gmail.com>
License-File: LICENSE
Classifier: License :: OSI Approved :: MIT License
Classifier: Operating System :: OS Independent
Classifier: Programming Language :: Python :: 3
Requires-Python: >=3.7
